setup.py
swipt/__init__.py
swipt/logo.py
swipt.egg-info/PKG-INFO
swipt.egg-info/SOURCES.txt
swipt.egg-info/dependency_links.txt
swipt.egg-info/top_level.txt
swipt/people/__init__.py
swipt/people/antonio.py
swipt/people/carlos.py
swipt/people/jaime.py
swipt/people/jessi.py
swipt/people/jorge.py
swipt/people/mario.py
swipt/people/miguel.py
swipt/people/patxi.py