Metadata-Version: 1.1
Name: swipt
Version: 0.1.1
Summary: StoneWork Is Pedro Ten
Home-page: https://github.com/stoneworksolutions/swipt
Author: StoneWork Solutions
Author-email: dev@stoneworksolutions.net
License: UNKNOWN
Download-URL: https://github.com/stoneworksolutions/swipt/tarball/0.1.1
Keywords: swipt,pedroten,stonework
Platform: UNKNOWN
